{"Base": {"Occurrences": 4.0, "Overall Time": 2000.14, "Mean": 500.035, "Variance": 750090002.7305, "Standard Deviation": 866.0773653262738}, "Base,FeatureB": {"Occurrences": 1.0, "Overall Time": 2000.105, "Mean": 2000.105, "Variance": 0.0, "Standard Deviation": 0.0}, "Base,FeatureC": {"Occurrences": 2.0, "Overall Time": 1000.092, "Mean": 500.046, "Variance": 250046002.116, "Standard Deviation": 500.046}, "Overall time for all features": {"Time Taken": 5000.3369999999995}, "Number of Repetitions": {"Repetitions": 30}}