{"Base": {"Occurrences": 86404, "Overall Time": 16921.089, "Mean": 0.19583687097819547, "Variance": 1200412.180508144, "Standard Deviation": 34.646964953775445}, "Base,Stdout": {"Occurrences": 14, "Overall Time": 0.011, "Mean": 0.0007857142857142857, "Variance": 0.00016836734693877556, "Standard Deviation": 0.000410325903324145}, "Base,Filter": {"Occurrences": 1, "Overall Time": 0.0, "Mean": 0.0, "Variance": 0.0, "Standard Deviation": 0.0}, "Base,Verbosity": {"Occurrences": 7, "Overall Time": 0.002, "Mean": 0.0002857142857142857, "Variance": 0.0002040816326530612, "Standard Deviation": 0.0004517539514526256}, "Base,FlushTO_val": {"Occurrences": 4, "Overall Time": 0.007, "Mean": 0.00175, "Variance": 0.0091875, "Standard Deviation": 0.003031088913245535}, "Base,FlushTO_val,Threads_val": {"Occurrences": 5, "Overall Time": 0.031, "Mean": 0.0062, "Variance": 0.14176000000000002, "Standard Deviation": 0.011906300852909774}, "Base,Cores,FlushTO_val,Threads_val": {"Occurrences": 3, "Overall Time": 0.001, "Mean": 0.0003333333333333333, "Variance": 0.00022222222222222223, "Standard Deviation": 0.0004714045207910317}, "Base,Cores,FlushTO_val": {"Occurrences": 1, "Overall Time": 0.0, "Mean": 0.0, "Variance": 0.0, "Standard Deviation": 0.0}, "Base,Cores": {"Occurrences": 1, "Overall Time": 0.001, "Mean": 0.001, "Variance": 0.0, "Standard Deviation": 0.0}, "Base,ForceOverwrite,Stdout": {"Occurrences": 6, "Overall Time": 0.488, "Mean": 0.08133333333333333, "Variance": 13.422222222222224, "Standard Deviation": 0.11585431464655178}, "Base,ForceOverwrite,KeepIn,Stdout": {"Occurrences": 2, "Overall Time": 0.001, "Mean": 0.0005, "Variance": 0.00025, "Standard Deviation": 0.0005}, "Base,Threads_val": {"Occurrences": 86381, "Overall Time": 71.125, "Mean": 0.0008233870874382097, "Variance": 0.0006179552610638603, "Standard Deviation": 0.0007861013045809428}, "Base,KeepIn": {"Occurrences": 2, "Overall Time": 0.001, "Mean": 0.0005, "Variance": 0.00025, "Standard Deviation": 0.0005}, "Overall time for all features": {"Time Taken": 16992.757}}