{"Base": {"Occurrences": 86404, "Overall Time": 59375.171, "Mean": 0.6871808133882691, "Variance": 1000.3250025479423, "Standard Deviation": 1.0001624880727844}, "Base,Stdout": {"Occurrences": 14, "Overall Time": 0.008, "Mean": 0.0005714285714285714, "Variance": 0.00038775510204081627, "Standard Deviation": 0.0006226998490772391}, "Base,Filter": {"Occurrences": 1, "Overall Time": 0.001, "Mean": 0.001, "Variance": 0.0, "Standard Deviation": 0.0}, "Base,Verbosity": {"Occurrences": 7, "Overall Time": 0.002, "Mean": 0.0002857142857142857, "Variance": 0.0002040816326530612, "Standard Deviation": 0.0004517539514526256}, "Base,FlushTO_val": {"Occurrences": 3, "Overall Time": 0.034, "Mean": 0.011333333333333334, "Variance": 0.23488888888888884, "Standard Deviation": 0.015326085243430196}, "Base,FlushTO_val,Threads_val": {"Occurrences": 1, "Overall Time": 0.0, "Mean": 0.0, "Variance": 0.0, "Standard Deviation": 0.0}, "Base,Cores,FlushTO_val": {"Occurrences": 1, "Overall Time": 0.0, "Mean": 0.0, "Variance": 0.0, "Standard Deviation": 0.0}, "Base,Cores": {"Occurrences": 1, "Overall Time": 0.001, "Mean": 0.001, "Variance": 0.0, "Standard Deviation": 0.0}, "Base,ForceOverwrite,Stdout": {"Occurrences": 6, "Overall Time": 0.829, "Mean": 0.13816666666666666, "Variance": 48.367472222222226, "Standard Deviation": 0.21992606080731367}, "Base,ForceOverwrite,KeepIn,Stdout": {"Occurrences": 2, "Overall Time": 0.0, "Mean": 0.0, "Variance": 0.0, "Standard Deviation": 0.0}, "Base,Threads_val": {"Occurrences": 86381, "Overall Time": 86.287, "Mean": 0.000998911797733298, "Variance": 0.06708697396081297, "Standard Deviation": 0.008190663829068617}, "Base,KeepIn": {"Occurrences": 2, "Overall Time": 0.001, "Mean": 0.0005, "Variance": 0.00025, "Standard Deviation": 0.0005}, "Overall time for all features": {"Time Taken": 59462.33399999999}}