{"Base": {"Occurrences": 86404, "Overall Time": 108362.441, "Mean": 1.2541368570899494, "Variance": 3630.0445230853306, "Standard Deviation": 1.9052675725696198}, "Base,Stdout": {"Occurrences": 14, "Overall Time": 0.009, "Mean": 0.0006428571428571429, "Variance": 0.0005153061224489797, "Standard Deviation": 0.0007178482586514922}, "Base,Filter": {"Occurrences": 1, "Overall Time": 0.001, "Mean": 0.001, "Variance": 0.0, "Standard Deviation": 0.0}, "Base,Verbosity": {"Occurrences": 7, "Overall Time": 0.004, "Mean": 0.0005714285714285714, "Variance": 0.00024489795918367346, "Standard Deviation": 0.0004948716593053935}, "Base,FlushTO_val": {"Occurrences": 3, "Overall Time": 0.035, "Mean": 0.011666666666666665, "Variance": 0.24955555555555556, "Standard Deviation": 0.01579732748143038}, "Base,FlushTO_val,Threads_val": {"Occurrences": 1, "Overall Time": 0.0, "Mean": 0.0, "Variance": 0.0, "Standard Deviation": 0.0}, "Base,Cores,FlushTO_val": {"Occurrences": 1, "Overall Time": 0.0, "Mean": 0.0, "Variance": 0.0, "Standard Deviation": 0.0}, "Base,Cores": {"Occurrences": 1, "Overall Time": 0.001, "Mean": 0.001, "Variance": 0.0, "Standard Deviation": 0.0}, "Base,ForceOverwrite,Stdout": {"Occurrences": 6, "Overall Time": 0.812, "Mean": 0.13533333333333333, "Variance": 38.08822222222222, "Standard Deviation": 0.19516204093578807}, "Base,ForceOverwrite,KeepIn,Stdout": {"Occurrences": 2, "Overall Time": 0.002, "Mean": 0.001, "Variance": 0.0, "Standard Deviation": 0.0}, "Base,Threads_val": {"Occurrences": 86381, "Overall Time": 127.264, "Mean": 0.0014732869496764333, "Variance": 14.979212970556446, "Standard Deviation": 0.12238959502570651}, "Base,KeepIn": {"Occurrences": 2, "Overall Time": 0.002, "Mean": 0.001, "Variance": 0.0, "Standard Deviation": 0.0}, "Overall time for all features": {"Time Taken": 108490.57100000001}}