{"Base": {"Occurrences": 86404, "Overall Time": 3784.556, "Mean": 0.04380070367112634, "Variance": 1134.7712966311424, "Standard Deviation": 1.0652564464161398}, "Base,Stdout": {"Occurrences": 14, "Overall Time": 0.008, "Mean": 0.0005714285714285714, "Variance": 0.00024489795918367346, "Standard Deviation": 0.0004948716593053935}, "Base,Filter": {"Occurrences": 1, "Overall Time": 0.0, "Mean": 0.0, "Variance": 0.0, "Standard Deviation": 0.0}, "Base,Verbosity": {"Occurrences": 7, "Overall Time": 0.003, "Mean": 0.00042857142857142855, "Variance": 0.00024489795918367346, "Standard Deviation": 0.0004948716593053934}, "Base,FlushTO_val": {"Occurrences": 4, "Overall Time": 0.008, "Mean": 0.002, "Variance": 0.012, "Standard Deviation": 0.0034641016151377543}, "Base,FlushTO_val,Threads_val": {"Occurrences": 5, "Overall Time": 0.031, "Mean": 0.0062, "Variance": 0.15376, "Standard Deviation": 0.0124}, "Base,Cores,FlushTO_val,Threads_val": {"Occurrences": 3, "Overall Time": 0.001, "Mean": 0.0003333333333333333, "Variance": 0.00022222222222222223, "Standard Deviation": 0.0004714045207910317}, "Base,Cores,FlushTO_val": {"Occurrences": 1, "Overall Time": 0.0, "Mean": 0.0, "Variance": 0.0, "Standard Deviation": 0.0}, "Base,Cores": {"Occurrences": 1, "Overall Time": 0.001, "Mean": 0.001, "Variance": 0.0, "Standard Deviation": 0.0}, "Base,ForceOverwrite,Stdout": {"Occurrences": 6, "Overall Time": 0.629, "Mean": 0.10483333333333333, "Variance": 22.86680555555556, "Standard Deviation": 0.15121774219831335}, "Base,ForceOverwrite,KeepIn,Stdout": {"Occurrences": 2, "Overall Time": 0.0, "Mean": 0.0, "Variance": 0.0, "Standard Deviation": 0.0}, "Base,Threads_val": {"Occurrences": 86381, "Overall Time": 88.828, "Mean": 0.0010283279887938319, "Variance": 0.0007773894885613909, "Standard Deviation": 0.0008816969369127868}, "Base,KeepIn": {"Occurrences": 2, "Overall Time": 0.001, "Mean": 0.0005, "Variance": 0.00025, "Standard Deviation": 0.0005}, "Overall time for all features": {"Time Taken": 3874.0660000000003}}