{"Base": {"Occurrences": 86404, "Overall Time": 45175.425, "Mean": 0.5228395097449192, "Variance": 609.7435398532663, "Standard Deviation": 0.7808607685453703}, "Base,Stdout": {"Occurrences": 14, "Overall Time": 0.009, "Mean": 0.0006428571428571429, "Variance": 0.0002295918367346939, "Standard Deviation": 0.00047915742374995496}, "Base,Filter": {"Occurrences": 1, "Overall Time": 0.0, "Mean": 0.0, "Variance": 0.0, "Standard Deviation": 0.0}, "Base,Verbosity": {"Occurrences": 7, "Overall Time": 0.003, "Mean": 0.00042857142857142855, "Variance": 0.00024489795918367346, "Standard Deviation": 0.0004948716593053934}, "Base,FlushTO_val": {"Occurrences": 3, "Overall Time": 0.031, "Mean": 0.010333333333333333, "Variance": 0.21355555555555555, "Standard Deviation": 0.014613540144521982}, "Base,FlushTO_val,Threads_val": {"Occurrences": 1, "Overall Time": 0.0, "Mean": 0.0, "Variance": 0.0, "Standard Deviation": 0.0}, "Base,Cores,FlushTO_val": {"Occurrences": 1, "Overall Time": 0.0, "Mean": 0.0, "Variance": 0.0, "Standard Deviation": 0.0}, "Base,Cores": {"Occurrences": 1, "Overall Time": 0.001, "Mean": 0.001, "Variance": 0.0, "Standard Deviation": 0.0}, "Base,ForceOverwrite,Stdout": {"Occurrences": 6, "Overall Time": 0.834, "Mean": 0.139, "Variance": 39.963, "Standard Deviation": 0.19990747859947613}, "Base,ForceOverwrite,KeepIn,Stdout": {"Occurrences": 2, "Overall Time": 0.002, "Mean": 0.001, "Variance": 0.0, "Standard Deviation": 0.0}, "Base,Threads_val": {"Occurrences": 86381, "Overall Time": 87.344, "Mean": 0.0010111482849237679, "Variance": 0.05498244132623632, "Standard Deviation": 0.007415014587054857}, "Base,KeepIn": {"Occurrences": 2, "Overall Time": 0.002, "Mean": 0.001, "Variance": 0.0, "Standard Deviation": 0.0}, "Overall time for all features": {"Time Taken": 45263.651}}