{"Base": {"Occurrences": 86404, "Overall Time": 23463.521, "Mean": 0.2715559580574973, "Variance": 1669082.4923378131, "Standard Deviation": 40.85440603334985}, "Base,Stdout": {"Occurrences": 14, "Overall Time": 0.008, "Mean": 0.0005714285714285714, "Variance": 0.00024489795918367346, "Standard Deviation": 0.0004948716593053935}, "Base,Filter": {"Occurrences": 1, "Overall Time": 0.0, "Mean": 0.0, "Variance": 0.0, "Standard Deviation": 0.0}, "Base,Verbosity": {"Occurrences": 7, "Overall Time": 0.003, "Mean": 0.00042857142857142855, "Variance": 0.00024489795918367346, "Standard Deviation": 0.0004948716593053934}, "Base,FlushTO_val": {"Occurrences": 4, "Overall Time": 0.006, "Mean": 0.0015, "Variance": 0.00675, "Standard Deviation": 0.002598076211353316}, "Base,FlushTO_val,Threads_val": {"Occurrences": 5, "Overall Time": 0.031, "Mean": 0.0062, "Variance": 0.14176000000000002, "Standard Deviation": 0.011906300852909774}, "Base,Cores,FlushTO_val,Threads_val": {"Occurrences": 3, "Overall Time": 0.003, "Mean": 0.001, "Variance": 0.0, "Standard Deviation": 0.0}, "Base,Cores,FlushTO_val": {"Occurrences": 1, "Overall Time": 0.001, "Mean": 0.001, "Variance": 0.0, "Standard Deviation": 0.0}, "Base,Cores": {"Occurrences": 1, "Overall Time": 0.0, "Mean": 0.0, "Variance": 0.0, "Standard Deviation": 0.0}, "Base,ForceOverwrite,Stdout": {"Occurrences": 6, "Overall Time": 0.515, "Mean": 0.08583333333333333, "Variance": 14.649472222222224, "Standard Deviation": 0.12103500411956132}, "Base,ForceOverwrite,KeepIn,Stdout": {"Occurrences": 2, "Overall Time": 0.0, "Mean": 0.0, "Variance": 0.0, "Standard Deviation": 0.0}, "Base,Threads_val": {"Occurrences": 86381, "Overall Time": 69.707, "Mean": 0.000806971440478809, "Variance": 0.0006367770898524405, "Standard Deviation": 0.0007979831388271562}, "Base,KeepIn": {"Occurrences": 2, "Overall Time": 0.002, "Mean": 0.001, "Variance": 0.0, "Standard Deviation": 0.0}, "Overall time for all features": {"Time Taken": 23533.797000000002}}