{"Base": {"Occurrences": 86404, "Overall Time": 38475.518, "Mean": 0.44529787972779034, "Variance": 2960122.7643095134, "Standard Deviation": 54.4070102496867}, "Base,Stdout": {"Occurrences": 14, "Overall Time": 0.009, "Mean": 0.0006428571428571429, "Variance": 0.00037244897959183684, "Standard Deviation": 0.0006102859818083951}, "Base,Filter": {"Occurrences": 1, "Overall Time": 0.0, "Mean": 0.0, "Variance": 0.0, "Standard Deviation": 0.0}, "Base,Verbosity": {"Occurrences": 7, "Overall Time": 0.004, "Mean": 0.0005714285714285714, "Variance": 0.00024489795918367346, "Standard Deviation": 0.0004948716593053935}, "Base,FlushTO_val": {"Occurrences": 4, "Overall Time": 0.011, "Mean": 0.00275, "Variance": 0.0131875, "Standard Deviation": 0.0036314597615834873}, "Base,FlushTO_val,Threads_val": {"Occurrences": 5, "Overall Time": 0.031, "Mean": 0.0062, "Variance": 0.15376, "Standard Deviation": 0.0124}, "Base,Cores,FlushTO_val,Threads_val": {"Occurrences": 3, "Overall Time": 0.0, "Mean": 0.0, "Variance": 0.0, "Standard Deviation": 0.0}, "Base,Cores,FlushTO_val": {"Occurrences": 1, "Overall Time": 0.0, "Mean": 0.0, "Variance": 0.0, "Standard Deviation": 0.0}, "Base,Cores": {"Occurrences": 1, "Overall Time": 0.001, "Mean": 0.001, "Variance": 0.0, "Standard Deviation": 0.0}, "Base,ForceOverwrite,Stdout": {"Occurrences": 6, "Overall Time": 0.531, "Mean": 0.0885, "Variance": 16.06225, "Standard Deviation": 0.1267369322652241}, "Base,ForceOverwrite,KeepIn,Stdout": {"Occurrences": 2, "Overall Time": 0.001, "Mean": 0.0005, "Variance": 0.00025, "Standard Deviation": 0.0005}, "Base,Threads_val": {"Occurrences": 86381, "Overall Time": 64.38, "Mean": 0.0007453027864924001, "Variance": 0.0006975076302152012, "Standard Deviation": 0.0008351692225023629}, "Base,KeepIn": {"Occurrences": 2, "Overall Time": 0.001, "Mean": 0.0005, "Variance": 0.00025, "Standard Deviation": 0.0005}, "Overall time for all features": {"Time Taken": 38540.48699999999}}